bazaar_ai/__init__.py
bazaar_ai/bazaar.py
bazaar_ai/coins.py
bazaar_ai/goods.py
bazaar_ai/market.py
bazaar_ai/trader.py
bazaar_ai/simulator/__init__.py
bazaar_ai/simulator/cli.py
bazaar_ai/simulator/server.py
bazaar_ai/simulator/agents/__init__.py
bazaar_ai/simulator/agents/random_agent.py
bazaar_ai/simulator/agents/simple_agent.py
bazaar_ai/simulator/static/index.html
bazaar_ai-0.9.3.dist-info/licenses/LICENSE.txt
bazaar_ai-0.9.3.dist-info/METADATA
bazaar_ai-0.9.3.dist-info/WHEEL
bazaar_ai-0.9.3.dist-info/entry_points.txt
bazaar_ai-0.9.3.dist-info/top_level.txt
bazaar_ai-0.9.3.dist-info/RECORD
