Metadata-Version: 2.4
Name: bazaar-ai
Version: 0.9.3
Summary: A simulation environment for training AI agents to play Jaipur
Author-email: Chandra Gummaluru <chandra.gummaluru@mail.utoronto.ca>
License: MIT
Project-URL: Homepage, https://github.com/chandra-gummaluru/bazaar_ai
Project-URL: Documentation, https://github.com/chandra-gummaluru/bazaar_ai/docs
Project-URL: Repository, https://github.com/chandra-gummaluru/bazaar_ai
Project-URL: Bug Tracker, https://github.com/chandra-gummaluru/bazaar_ai/issues
Keywords: reinforcement-learning,game,ai,jaipur,simulation
Classifier: Development Status :: 4 - Beta
Classifier: Intended Audience :: Education
Classifier: Intended Audience :: Science/Research
Classifier: License :: OSI Approved :: MIT License
Classifier: Programming Language :: Python :: 3
Classifier: Programming Language :: Python :: 3.8
Classifier: Programming Language :: Python :: 3.9
Classifier: Programming Language :: Python :: 3.10
Classifier: Programming Language :: Python :: 3.11
Classifier: Programming Language :: Python :: 3.12
Classifier: Topic :: Scientific/Engineering :: Artificial Intelligence
Requires-Python: >=3.8
License-File: LICENSE.txt
Requires-Dist: arelai
Requires-Dist: websockets
Requires-Dist: rich
Provides-Extra: dev
Requires-Dist: pytest>=7.0; extra == "dev"
Requires-Dist: black>=23.0; extra == "dev"
Requires-Dist: flake8>=6.0; extra == "dev"
Dynamic: license-file
